pymavi/__init__.py
pymavi/client.py
pymavi/exceptions.py
pymavi-0.1.7.dist-info/licenses/LICENSE
pymavi-0.1.7.dist-info/METADATA
pymavi-0.1.7.dist-info/WHEEL
pymavi-0.1.7.dist-info/top_level.txt
pymavi-0.1.7.dist-info/RECORD
