Metadata-Version: 2.4
Name: pymavi
Version: 0.1.7
Summary: Python SDK for the Mavi Video AI Platform
Author-email: OpenInterX <support@openinterx.com>
License: MIT
Project-URL: Homepage, https://github.com/OpenInterX/pymavi
Classifier: Development Status :: 4 - Beta
Classifier: Intended Audience :: Developers
Classifier: License :: OSI Approved :: MIT License
Classifier: Operating System :: OS Independent
Classifier: Programming Language :: Python :: 3
Classifier: Programming Language :: Python :: 3.8
Classifier: Programming Language :: Python :: 3.9
Classifier: Programming Language :: Python :: 3.10
Classifier: Programming Language :: Python :: 3.11
Requires-Python: >=3.8
License-File: LICENSE
Requires-Dist: certifi==2025.1.31
Requires-Dist: charset-normalizer==3.4.1
Requires-Dist: idna==3.10
Requires-Dist: python-dotenv==1.1.0
Requires-Dist: requests==2.32.3
Requires-Dist: setuptools==75.8.0
Requires-Dist: urllib3==2.3.0
Requires-Dist: wheel==0.45.1
Requires-Dist: yt-dlp==2025.2.19
Dynamic: license-file
